LICENSE
MANIFEST.in
README.md
setup.py
tests/__init__.py
tests/mocks/__init__.py
tests/mocks/mock_driver.py
tests/mocks/mock_failing_driver.py
tests/mocks/mock_value_driver.py
tests/unit/__init__.py
tests/unit/drivers/__init__.py
tests/unit/drivers/test_disk_memory_driver.py
tests/unit/drivers/test_prompt_driver.py
tests/unit/memory/__init__.py
tests/unit/memory/test_pipeline_buffer_memory.py
tests/unit/memory/test_pipeline_memory.py
tests/unit/memory/test_pipeline_summary_memory.py
tests/unit/schemas/__init__.py
tests/unit/schemas/test_pipeline_schema.py
tests/unit/schemas/test_workflow_schema.py
tests/unit/steps/__init__.py
tests/unit/steps/test_prompt_step.py
tests/unit/steps/test_tool_step.py
tests/unit/steps/test_toolkit_step.py
tests/unit/structures/__init__.py
tests/unit/structures/test_pipeline.py
tests/unit/structures/test_workflow.py
tests/unit/utils/__init__.py
tests/unit/utils/test_command_runner.py
tests/unit/utils/test_conversation.py
tests/unit/utils/test_python_runner.py
tests/unit/utils/test_tiktoken_tokenizer.py
warpspeed/__init__.py
warpspeed.egg-info/PKG-INFO
warpspeed.egg-info/SOURCES.txt
warpspeed.egg-info/dependency_links.txt
warpspeed.egg-info/requires.txt
warpspeed.egg-info/top_level.txt
warpspeed/artifacts/__init__.py
warpspeed/artifacts/error_output.py
warpspeed/artifacts/structure_artifact.py
warpspeed/artifacts/text_output.py
warpspeed/drivers/__init__.py
warpspeed/drivers/memory/__init__.py
warpspeed/drivers/memory/disk_memory_driver.py
warpspeed/drivers/memory/memory_driver.py
warpspeed/drivers/prompt/__init__.py
warpspeed/drivers/prompt/openai_prompt_driver.py
warpspeed/drivers/prompt/prompt_driver.py
warpspeed/memory/__init__.py
warpspeed/memory/buffer_pipeline_memory.py
warpspeed/memory/pipeline_memory.py
warpspeed/memory/pipeline_run.py
warpspeed/memory/summary_pipeline_memory.py
warpspeed/rules/__init__.py
warpspeed/rules/json.py
warpspeed/rules/meta.py
warpspeed/rules/rule.py
warpspeed/schemas/__init__.py
warpspeed/schemas/base_schema.py
warpspeed/schemas/openai_prompt_driver_schema.py
warpspeed/schemas/pipeline_schema.py
warpspeed/schemas/polymorphic_schema.py
