Metadata-Version: 2.1
Name: warpspeed
Version: 0.7.0
Summary: Python framework for AI workflows and pipelines.
Home-page: https://github.com/usewarpspeed/warpspeed
Author: Vasily Vasinov
Author-email: hello@warpspeed.cc
License: Apache 2.0
License-File: LICENSE
